pydaily/__init__.py
pydaily/setup.py
pydaily/filesystem/__init__.py
pydaily/filesystem/_file.py
pydaily/filesystem/_folder.py
pydaily/filesystem/_rename.py
pydaily/filesystem/_suffix.py
pydaily/filesystem/setup.py
pydaily/format/__init__.py
pydaily/format/_csv.py
pydaily/format/_h5.py
pydaily/format/_json.py
pydaily/format/_pickle.py
pydaily/format/_txt.py
pydaily/format/setup.py
pydaily/img/__init__.py
pydaily/img/_convert.py
pydaily/img/setup.py
pydaily/log/__init__.py
pydaily/log/_log.py
pydaily/log/setup.py
pydaily/mtm/__init__.py
pydaily/mtm/_tokenizer.py
pydaily/mtm/setup.py
pydaily/tic/__init__.py
pydaily/tic/_elapse.py
pydaily/tic/setup.py
pydaily-0.4.4.dist-info/LICENSE
pydaily-0.4.4.dist-info/METADATA
pydaily-0.4.4.dist-info/WHEEL
pydaily-0.4.4.dist-info/top_level.txt
pydaily-0.4.4.dist-info/RECORD
