Metadata-Version: 2.1
Name: pydaily
Version: 0.4.4
Summary: Daily python utility functions.
Home-page: https://github.com/PingjunChen/pydaily
Author: Pingjun Chen
Author-email: pingjunchen@ieee.org
License: Apache
Platform: UNKNOWN
Classifier: Development Status :: 1 - Planning
Classifier: Intended Audience :: Developers
Classifier: Intended Audience :: Science/Research
Classifier: License :: OSI Approved :: Apache Software License
Classifier: Programming Language :: Python
Classifier: Programming Language :: Python :: 3
Classifier: Programming Language :: Python :: 3.8
Classifier: Topic :: Scientific/Engineering
Requires-Dist: numpy (>=1.20.0)
Requires-Dist: opencv-python (>=4.4.0.40)
Requires-Dist: scikit-image (>=0.18.0)
Requires-Dist: pandas (>=1.2.0)
Requires-Dist: deepdish (>=0.3.6)
